[
    {
        "old":  "About Image (1).png",
        "new":  "About-Image-1.png"
    },
    {
        "old":  "About Image.png",
        "new":  "About-Image.png"
    },
    {
        "old":  "facebook.svg",
        "new":  "facebook-1.svg"
    },
    {
        "old":  "Featue 4 Image.png",
        "new":  "Featue-4-Image.png"
    },
    {
        "old":  "Feature 1 Image.png",
        "new":  "Feature-1-Image.png"
    },
    {
        "old":  "Feature 2 image.png",
        "new":  "Feature-2-image.png"
    },
    {
        "old":  "Feature 3 Image.png",
        "new":  "Feature-3-Image.png"
    },
    {
        "old":  "Feature 5 Image.png",
        "new":  "Feature-5-Image.png"
    },
    {
        "old":  "Header image (1).png",
        "new":  "Header-image-1.png"
    },
    {
        "old":  "Header Image (2).png",
        "new":  "Header-Image-2.png"
    },
    {
        "old":  "Header Image.png",
        "new":  "Header-Image.png"
    },
    {
        "old":  "Icon (1).svg",
        "new":  "Icon-1.svg"
    },
    {
        "old":  "Icon (2).svg",
        "new":  "Icon-2.svg"
    },
    {
        "old":  "Icon (3).svg",
        "new":  "Icon-3.svg"
    },
    {
        "old":  "Image (1).png",
        "new":  "Image-1.png"
    },
    {
        "old":  "Image (1).svg",
        "new":  "Image-1.svg"
    },
    {
        "old":  "Image (2).png",
        "new":  "Image-2.png"
    },
    {
        "old":  "Image (2).svg",
        "new":  "Image-2.svg"
    },
    {
        "old":  "Image (3).svg",
        "new":  "Image-3.svg"
    },
    {
        "old":  "Image (4).svg",
        "new":  "Image-4.svg"
    },
    {
        "old":  "Image 1.svg",
        "new":  "Image-1-1.svg"
    },
    {
        "old":  "Image 2.svg",
        "new":  "Image-2-1.svg"
    },
    {
        "old":  "Image 3.svg",
        "new":  "Image-3-1.svg"
    },
    {
        "old":  "Image 4.svg",
        "new":  "Image-4-1.svg"
    },
    {
        "old":  "Image.png",
        "new":  "Image-3.png"
    },
    {
        "old":  "Image.svg",
        "new":  "Image-5.svg"
    },
    {
        "old":  "instagram.svg",
        "new":  "instagram-1.svg"
    },
    {
        "old":  "Logo (1).svg",
        "new":  "Logo-1.svg"
    },
    {
        "old":  "Logo (2).svg",
        "new":  "Logo-2.svg"
    },
    {
        "old":  "Logo (3).svg",
        "new":  "Logo-3.svg"
    },
    {
        "old":  "logo-icon (1).svg",
        "new":  "logo-icon-1.svg"
    },
    {
        "old":  "logo-icon.svg",
        "new":  "logo-icon-2.svg"
    },
    {
        "old":  "Logo.svg",
        "new":  "Logo-4.svg"
    },
    {
        "old":  "map-placeholder.svg",
        "new":  "map-placeholder-1.svg"
    },
    {
        "old":  "Map.svg",
        "new":  "Map-1.svg"
    },
    {
        "old":  "Service image.png",
        "new":  "Service-image.png"
    },
    {
        "old":  "twitter.svg",
        "new":  "twitter-1.svg"
    },
    {
        "old":  "Vector.svg",
        "new":  "Vector-1.svg"
    },
    {
        "old":  "youtube.svg",
        "new":  "youtube-1.svg"
    }
]
